dash_dot.v
module dash_dot ( input clk,input dataIn ,output valueReady, output[1:0]dataOut
  
);
reg[1:0] dataOut;
reg valueReady;
reg [3:0] state;

wire clk;

always @(posedge clk ) begin
case (state)
  4'd0:begin
    valueReady <= 1'b0;
    if (dataIn == 1'b1) begin
      state <= 4'd3; //state <= 3'd1;
    end
    else if(dataIn == 1'b0)begin
      state <= 4'd2;
    end
  end
  4'd1:begin
    valueReady <= 1'b0; // newEd
    if (dataIn == 1'b1) begin
      state <= 4'd5;
    end else if(dataIn == 1'b0) begin
      state <= 4'd7; // newEd 4'd2
    end
  end
  4'd2:begin
  valueReady <= 1'b0;
  if (dataIn == 1'b1) begin
      state <= 4'd3;
  end else if(dataIn == 1'b0) begin
      state <= 4'd4;
    end
  end
  4'd3:begin // ******* outPut Dots ********
    if (dataIn == 1'b1) begin
      valueReady <= 1'b0;
      state <= 3'd2; // edit new
    end else if(dataIn == 1'b0) begin
      state <= 4'd0;
      valueReady <= 1'b1;
      dataOut <= 00;
    end
    
  end
  4'd4:begin // ******* outPut Space ********
    valueReady <= 1'b1;
    dataOut <= 10;
    if (dataIn == 1'b1) begin
      state <= 4'd1;
    end else if(dataIn == 1'b0) begin
      state <= 4'd0;
    end
  end
  4'd5:begin
    if (dataIn == 1'b1) begin
      state <= 4'd6;
    end else if(dataIn == 1'b0) begin
      state <= 4'd0;
    end
  end
  4'd6:begin  // ******* outPut Dash ********
    state <= 4'd1;
    valueReady <= 1'b1;
    dataOut <= 2'b11;
  end
  4'd7:begin
    if(dataIn == 1'b0)begin
      state <= 4'd8;
    end else if(dataIn == 1'b1) begin
      state <= 3'd5;
    end
  end
  4'd8:begin
    if(dataIn == 1'b0)begin // ******* outPut Space ********
      state <= 4'd2;
      valueReady <= 1'b1;
      dataOut <= 2'b10;
    end
  end

  default:begin
    state <= 4'd0;
    valueReady <= 1'b0;
    dataOut <= 01;
  end
endcase

end
endmodule // 

//ME:
//iverilog sos_detector.v
//iverilog -o a.out sos_detector_tb.v
//vvp a.out
// open -a Scansion sos_detector_tb.vcd

sos_driver.v
module sos_driver ( input clk,output dataOut
  
);

reg dataOut;
reg [3:0]state;
reg dotflag;
reg dashflag;
reg startCounterB;
reg [4:0] counter;
reg [4:0] counterB;

wire clk;

always @(posedge clk)begin
    counter <= counter +1;
    if(counter == 4'd5)begin // counter == 4'd5
        dotflag <= 1'b1;
        counter <= 4'd0; 
    end
    if(startCounterB == 1'b1)begin
        counterB <= counterB+1;
    end
    if (counterB == 4'd9) begin
      dashflag <=1'b1;
      counterB <=4'd0;
    end
    case (state)
      4'd0: begin
        dataOut <= 1'b0;
        if (dotflag == 1'b0) begin
            state <= 3'd1;
        end else begin
            state <= 3'd3;
        end
      end
      4'd1:begin
        dataOut <= 1'b1;
        if(dotflag == 1'b0)begin
            state <= 3'd0;//***CH
        end else begin
            if (dashflag == 1'b0) begin
              state <= 3'd5;
              counter <=4'd00; 
              startCounterB <= 1'b1;
            end
        end
      end
      4'd2:begin
        dataOut <= 1'b0;
        state <= 3'd0; 
      end
      4'd3:begin
        dataOut <= 1'b0;
        state <= 3'd4; 
        dashflag <=1'b0; //*****CH
      end
      4'd4:begin
        dataOut <= 1'b0;
        if (dashflag == 1'b0) begin
          state <= 3'd1; 
        end else begin
          state <= 3'd0;
          dotflag <= 1'b0; 
        end
      end
      4'd5:begin
        dataOut <= 1'b1;
        state <= 3'd6; 
      end
      4'd6:begin
        dataOut <= 1'b1;
        state <= 3'd7; 
      end
      4'd7:begin
        dataOut <= 1'b0;
        if (dashflag == 1'b0) begin
          state <= 3'd1;
        end else begin
          state <= 3'd4; //**** chp 3'd3;
          startCounterB <= 1'b0;
          counter <= 4'd5; //***chp 3'd0
        end 
      end
      default: begin
        state <=3'd0;
        dotflag <= 1'b0;
        dashflag <= 1'b0;
        counter <=2'b00;
        counterB <=5'd0;
        startCounterB<=0;
        //dataOut <= 1'b0;
      end
    endcase
  
end

endmodule // 


//ME:
//iverilog sos_driver.v
//iverilog -o a.out sos_driver_tb.v
//vvp a.out
// open -a scansion sos_driver_tb.vcd

dash_dot_tb.v
`timescale 1ns/100ps
`include "sos_driver.v"
`include "dash_dot.v"

module dash_dot_tb;

   integer k;
   integer clock = 1'b0;
   integer clockB = 1'b0;

   wire clkk;
   wire clkB;
   assign clkk = clock;
   assign clkB = clock;

   wire data_in;
   wire ready;
  
   wire[1:0]outPut;
   reg[1:0] prevOutput;
   reg[1:0] outz;



   //assign {A,B} = k;
   //sos_driver driver(.clk(clkk),.dataOut(data_in));
   sos_driver driver(clkk,data_in);
   dash_dot the_circuit(clkB,data_in,ready,outPut);
   
   always begin
        #10 clock = ~clock;
    end
    
   initial begin
      $dumpfile("dash_dot_tb.vcd");
      $dumpvars(0, dash_dot_tb);

// *********** Test Cases ********** //
        for (k=0; k<128; k=k+1)begin
            #10;
            if (ready == 1'b1 && outPut== 2'b00 && clock == 1'b0 ) begin
                $display("Signal = .");
            end else if(ready == 1'b1 && outPut== 2'b10 && clock == 1'b0  ) begin
                $display("Signal = Space");
            end else if(ready == 1'b1 && outPut== 2'b11 && clock == 1'b0 ) begin
                $display("Signal = _");
                end
        end
// *********** Detecting SOS ********** //

      $finish;
   end
   

endmodule

// To execute::>>
//iverilog dash_dot.v
//iverilog -o a.out dash_dot_tb.v
//vvp a.out
// open -a Scansion dash_dot_tb.vcd

dash_dot_tb.vcd
$date
	Sun Nov 19 12:32:52 2017
$end
$version
	Icarus Verilog
$end
$timescale
	100ps
$end
$scope module dash_dot_tb $end
$var wire 1 ! ready $end
$var wire 2 " outPut [1:0] $end
$var wire 1 # data_in $end
$var wire 1 $ clkk $end
$var wire 1 % clkB $end
$var integer 32 & clock [31:0] $end
$var integer 32 ' clockB [31:0] $end
$var integer 32 ( k [31:0] $end
$scope module driver $end
$var wire 1 $ clk $end
$var reg 5 ) counter [4:0] $end
$var reg 5 * counterB [4:0] $end
$var reg 1 + dashflag $end
$var reg 1 # dataOut $end
$var reg 1 , dotflag $end
$var reg 1 - startCounterB $end
$var reg 4 . state [3:0] $end
$upscope $end
$scope module the_circuit $end
$var wire 1 % clk $end
$var wire 1 # dataIn $end
$var reg 2 / dataOut [1:0] $end
$var reg 4 0 state [3:0] $end
$var reg 1 ! valueReady $end
$upscope $end
$upscope $end
$enddefinitions $end
#0
$dumpvars
bx 0
bx /
bx .
x-
x,
x+
bx *
bx )
b0 (
b0 '
b0 &
0%
0$
x#
bx "
x!
$end
#100
0-
b0 *
b0 )
0+
0,
b0 .
b1 "
b1 /
0!
b0 0
1$
1%
b1 (
b11111111111111111111111111111111 &
#200
0$
0%
b10 (
b0 &
#300
b1 .
0#
b1 )
1$
1%
b11 (
b11111111111111111111111111111111 &
#400
0$
0%
b100 (
b0 &
#500
b0 .
1#
b10 )
b10 0
1$
1%
b101 (
b11111111111111111111111111111111 &
#600
0$
0%
b110 (
b0 &
#700
b1 .
0#
b11 )
b11 0
1$
1%
b111 (
b11111111111111111111111111111111 &
#800
0$
0%
b1000 (
b0 &
#900
b0 .
1#
b100 )
b0 "
b0 /
1!
b0 0
1$
1%
b1001 (
b11111111111111111111111111111111 &
#1000
0$
0%
b1010 (
b0 &
#1100
b1 .
0#
b101 )
b11 0
0!
1$
1%
b1011 (
b11111111111111111111111111111111 &
#1200
0$
0%
b1100 (
b0 &
#1300
b0 .
1#
1,
b0 )
1!
b0 0
1$
1%
b1101 (
b11111111111111111111111111111111 &
#1400
0$
0%
b1110 (
b0 &
#1500
b11 .
0#
b1 )
b11 0
0!
1$
1%
b1111 (
b11111111111111111111111111111111 &
#1600
0$
0%
b10000 (
b0 &
#1700
b100 .
b10 )
1!
b0 0
1$
1%
b10001 (
b11111111111111111111111111111111 &
#1800
0$
0%
b10010 (
b0 &
#1900
b1 .
b11 )
b10 0
0!
1$
1%
b10011 (
b11111111111111111111111111111111 &
#2000
0$
0%
b10100 (
b0 &
#2100
1-
b101 .
1#
b0 )
b100 0
1$
1%
b10101 (
b11111111111111111111111111111111 &
#2200
0$
0%
b10110 (
b0 &
#2300
b110 .
b1 *
b1 )
b1 0
b10 "
b10 /
1!
1$
1%
b10111 (
b11111111111111111111111111111111 &
#2400
0$
0%
b11000 (
b0 &
#2500
b111 .
b10 *
b10 )
b101 0
0!
1$
1%
b11001 (
b11111111111111111111111111111111 &
#2600
0$
0%
b11010 (
b0 &
#2700
b1 .
0#
b11 *
b11 )
b110 0
1$
1%
b11011 (
b11111111111111111111111111111111 &
#2800
0$
0%
b11100 (
b0 &
#2900
b101 .
1#
b100 *
b0 )
b11 "
b11 /
1!
b1 0
1$
1%
b11101 (
b11111111111111111111111111111111 &
#3000
0$
0%
b11110 (
b0 &
#3100
b110 .
b101 *
b1 )
b101 0
0!
1$
1%
b11111 (
b11111111111111111111111111111111 &
#3200
0$
0%
b100000 (
b0 &
#3300
b111 .
b110 *
b10 )
b110 0
1$
1%
b100001 (
b11111111111111111111111111111111 &
#3400
0$
0%
b100010 (
b0 &
#3500
b1 .
0#
b111 *
b11 )
1!
b1 0
1$
1%
b100011 (
b11111111111111111111111111111111 &
#3600
0$
0%
b100100 (
b0 &
#3700
b101 .
1#
b1000 *
b0 )
b111 0
0!
1$
1%
b100101 (
b11111111111111111111111111111111 &
#3800
0$
0%
b100110 (
b0 &
#3900
b110 .
b1001 *
b1 )
b101 0
1$
1%
b100111 (
b11111111111111111111111111111111 &
#4000
0$
0%
b101000 (
b0 &
#4100
b111 .
1+
b0 *
b10 )
b110 0
1$
1%
b101001 (
b11111111111111111111111111111111 &
#4200
0$
0%
b101010 (
b0 &
#4300
0-
b100 .
0#
b1 *
b101 )
1!
b1 0
1$
1%
b101011 (
b11111111111111111111111111111111 &
#4400
0$
0%
b101100 (
b0 &
#4500
0,
b0 .
b0 )
b111 0
0!
1$
1%
b101101 (
b11111111111111111111111111111111 &
#4600
0$
0%
b101110 (
b0 &
#4700
b1 .
b1 )
b1000 0
1$
1%
b101111 (
b11111111111111111111111111111111 &
#4800
0$
0%
b110000 (
b0 &
#4900
b0 .
1#
b10 )
b10 "
b10 /
1!
b10 0
1$
1%
b110001 (
b11111111111111111111111111111111 &
#5000
0$
0%
b110010 (
b0 &
#5100
b1 .
0#
b11 )
b11 0
0!
1$
1%
b110011 (
b11111111111111111111111111111111 &
#5200
0$
0%
b110100 (
b0 &
#5300
b0 .
1#
b100 )
b0 "
b0 /
1!
b0 0
1$
1%
b110101 (
b11111111111111111111111111111111 &
#5400
0$
0%
b110110 (
b0 &
#5500
b1 .
0#
b101 )
b11 0
0!
1$
1%
b110111 (
b11111111111111111111111111111111 &
#5600
0$
0%
b111000 (
b0 &
#5700
b0 .
1#
1,
b0 )
1!
b0 0
1$
1%
b111001 (
b11111111111111111111111111111111 &
#5800
0$
0%
b111010 (
b0 &
#5900
b11 .
0#
b1 )
b11 0
0!
1$
1%
b111011 (
b11111111111111111111111111111111 &
#6000
0$
0%
b111100 (
b0 &
#6100
0+
b100 .
b10 )
1!
b0 0
1$
1%
b111101 (
b11111111111111111111111111111111 &
#6200
0$
0%
b111110 (
b0 &
#6300
b1 .
b11 )
b10 0
0!
1$
1%
b111111 (
b11111111111111111111111111111111 &
#6400
0$
0%
b1000000 (
b0 &
#6500
1-
b101 .
1#
b0 )
b100 0
1$
1%
b1000001 (
b11111111111111111111111111111111 &
#6600
0$
0%
b1000010 (
b0 &
#6700
b110 .
b10 *
b1 )
b1 0
b10 "
b10 /
1!
1$
1%
b1000011 (
b11111111111111111111111111111111 &
#6800
0$
0%
b1000100 (
b0 &
#6900
b111 .
b11 *
b10 )
b101 0
0!
1$
1%
b1000101 (
b11111111111111111111111111111111 &
#7000
0$
0%
b1000110 (
b0 &
#7100
b1 .
0#
b100 *
b11 )
b110 0
1$
1%
b1000111 (
b11111111111111111111111111111111 &
#7200
0$
0%
b1001000 (
b0 &
#7300
b101 .
1#
b101 *
b0 )
b11 "
b11 /
1!
b1 0
1$
1%
b1001001 (
b11111111111111111111111111111111 &
#7400
0$
0%
b1001010 (
b0 &
#7500
b110 .
b110 *
b1 )
b101 0
0!
1$
1%
b1001011 (
b11111111111111111111111111111111 &
#7600
0$
0%
b1001100 (
b0 &
#7700
b111 .
b111 *
b10 )
b110 0
1$
1%
b1001101 (
b11111111111111111111111111111111 &
#7800
0$
0%
b1001110 (
b0 &
#7900
b1 .
0#
b1000 *
b11 )
1!
b1 0
1$
1%
b1001111 (
b11111111111111111111111111111111 &
#8000
0$
0%
b1010000 (
b0 &
#8100
b101 .
1#
b1001 *
b0 )
b111 0
0!
1$
1%
b1010001 (
b11111111111111111111111111111111 &
#8200
0$
0%
b1010010 (
b0 &
#8300
b110 .
1+
b0 *
b1 )
b101 0
1$
1%
b1010011 (
b11111111111111111111111111111111 &
#8400
0$
0%
b1010100 (
b0 &
#8500
b111 .
b1 *
b10 )
b110 0
1$
1%
b1010101 (
b11111111111111111111111111111111 &
#8600
0$
0%
b1010110 (
b0 &
#8700
0-
b100 .
0#
b10 *
b101 )
1!
b1 0
1$
1%
b1010111 (
b11111111111111111111111111111111 &
#8800
0$
0%
b1011000 (
b0 &
#8900
0,
b0 .
b0 )
b111 0
0!
1$
1%
b1011001 (
b11111111111111111111111111111111 &
#9000
0$
0%
b1011010 (
b0 &
#9100
b1 .
b1 )
b1000 0
1$
1%
b1011011 (
b11111111111111111111111111111111 &
#9200
0$
0%
b1011100 (
b0 &
#9300
b0 .
1#
b10 )
b10 "
b10 /
1!
b10 0
1$
1%
b1011101 (
b11111111111111111111111111111111 &
#9400
0$
0%
b1011110 (
b0 &
#9500
b1 .
0#
b11 )
b11 0
0!
1$
1%
b1011111 (
b11111111111111111111111111111111 &
#9600
0$
0%
b1100000 (
b0 &
#9700
b0 .
1#
b100 )
b0 "
b0 /
1!
b0 0
1$
1%
b1100001 (
b11111111111111111111111111111111 &
#9800
0$
0%
b1100010 (
b0 &
#9900
b1 .
0#
b101 )
b11 0
0!
1$
1%
b1100011 (
b11111111111111111111111111111111 &
#10000
0$
0%
b1100100 (
b0 &
#10100
b0 .
1#
1,
b0 )
1!
b0 0
1$
1%
b1100101 (
b11111111111111111111111111111111 &
#10200
0$
0%
b1100110 (
b0 &
#10300
b11 .
0#
b1 )
b11 0
0!
1$
1%
b1100111 (
b11111111111111111111111111111111 &
#10400
0$
0%
b1101000 (
b0 &
#10500
0+
b100 .
b10 )
1!
b0 0
1$
1%
b1101001 (
b11111111111111111111111111111111 &
#10600
0$
0%
b1101010 (
b0 &
#10700
b1 .
b11 )
b10 0
0!
1$
1%
b1101011 (
b11111111111111111111111111111111 &
#10800
0$
0%
b1101100 (
b0 &
#10900
1-
b101 .
1#
b0 )
b100 0
1$
1%
b1101101 (
b11111111111111111111111111111111 &
#11000
0$
0%
b1101110 (
b0 &
#11100
b110 .
b11 *
b1 )
b1 0
b10 "
b10 /
1!
1$
1%
b1101111 (
b11111111111111111111111111111111 &
#11200
0$
0%
b1110000 (
b0 &
#11300
b111 .
b100 *
b10 )
b101 0
0!
1$
1%
b1110001 (
b11111111111111111111111111111111 &
#11400
0$
0%
b1110010 (
b0 &
#11500
b1 .
0#
b101 *
b11 )
b110 0
1$
1%
b1110011 (
b11111111111111111111111111111111 &
#11600
0$
0%
b1110100 (
b0 &
#11700
b101 .
1#
b110 *
b0 )
b11 "
b11 /
1!
b1 0
1$
1%
b1110101 (
b11111111111111111111111111111111 &
#11800
0$
0%
b1110110 (
b0 &
#11900
b110 .
b111 *
b1 )
b101 0
0!
1$
1%
b1110111 (
b11111111111111111111111111111111 &
#12000
0$
0%
b1111000 (
b0 &
#12100
b111 .
b1000 *
b10 )
b110 0
1$
1%
b1111001 (
b11111111111111111111111111111111 &
#12200
0$
0%
b1111010 (
b0 &
#12300
b1 .
0#
b1001 *
b11 )
1!
b1 0
1$
1%
b1111011 (
b11111111111111111111111111111111 &
#12400
0$
0%
b1111100 (
b0 &
#12500
b101 .
1#
1+
b0 *
b0 )
b111 0
0!
1$
1%
b1111101 (
b11111111111111111111111111111111 &
#12600
0$
0%
b1111110 (
b0 &
#12700
b110 .
b1 *
b1 )
b101 0
1$
1%
b1111111 (
b11111111111111111111111111111111 &
#12800
0$
0%
b10000000 (
b0 &
