sos_driver.v
module sos_driver ( input clk,output dataOut
  
);

reg dataOut;
reg [3:0]state;
reg dotflag;
reg dashflag;
reg startCounterB;
reg [4:0] counter;
reg [4:0] counterB;

wire clk;

always @(posedge clk)begin
    counter <= counter +1;
    if(counter == 4'd5)begin // counter == 4'd5
        dotflag <= 1'b1;
        counter <= 4'd0; 
    end
    if(startCounterB == 1'b1)begin
        counterB <= counterB+1;
    end
    if (counterB == 4'd9) begin
      dashflag <=1'b1;
      counterB <=4'd0;
    end
    case (state)
      4'd0: begin
        dataOut <= 1'b0;
        if (dotflag == 1'b0) begin
            state <= 3'd1;
        end else begin
            state <= 3'd3;
        end
      end
      4'd1:begin
        dataOut <= 1'b1;
        if(dotflag == 1'b0)begin
            state <= 3'd0;//***CH
        end else begin
            if (dashflag == 1'b0) begin
              state <= 3'd5;
              counter <=4'd00; 
              startCounterB <= 1'b1;
            end
        end
      end
      4'd2:begin
        dataOut <= 1'b0;
        state <= 3'd0; 
      end
      4'd3:begin
        dataOut <= 1'b0;
        state <= 3'd4; 
        dashflag <=1'b0; //*****CH
      end
      4'd4:begin
        dataOut <= 1'b0;
        if (dashflag == 1'b0) begin
          state <= 3'd1; 
        end else begin
          state <= 3'd0;
          dotflag <= 1'b0; 
        end
      end
      4'd5:begin
        dataOut <= 1'b1;
        state <= 3'd6; 
      end
      4'd6:begin
        dataOut <= 1'b1;
        state <= 3'd7; 
      end
      4'd7:begin
        dataOut <= 1'b0;
        if (dashflag == 1'b0) begin
          state <= 3'd1;
        end else begin
          state <= 3'd4; //**** chp 3'd3;
          startCounterB <= 1'b0;
          counter <= 4'd5; //***chp 3'd0
        end 
      end
      default: begin
        state <=3'd0;
        dotflag <= 1'b0;
        dashflag <= 1'b0;
        counter <=2'b00;
        counterB <=5'd0;
        startCounterB<=0;
        //dataOut <= 1'b0;
      end
    endcase
  
end

endmodule // 


//ME:
//iverilog sos_driver.v
//iverilog -o a.out sos_driver_tb.v
//vvp a.out
// open -a scansion sos_driver_tb.vcd

sos_driver_tb.v
`timescale 1ns/100ps
`include "sos_driver.v"

module sos_driver_tb;

   wire clkW, out;
   integer k=0;
   reg clk = 1'b0;
   assign clkW = clk;

   sos_driver the_circuit(.clk(clkW),.dataOut(out));

   initial begin

      $dumpfile("sos_driver.vcd");
      $dumpvars(0, sos_driver_tb);

      for (k=0; k<128; k=k+1)begin
            #10;
            clk = ~clk;
            $display("done testing case %d", k);
        end
      $finish;

   end


endmodule

// To execute::>>
//1- iverilog sos_driver.v
//2- iverilog -o a.out sos_driver_tb.v
//3- vvp a.out
//4 -open -a Scansion sos_driver.vcd

sos_driver.vcd
$date
	Sun Nov 19 02:22:27 2017
$end
$version
	Icarus Verilog
$end
$timescale
	100ps
$end
$scope module sos_driver_tb $end
$var wire 1 ! clkW $end
$var wire 1 " out $end
$var reg 1 # clk $end
$var integer 32 $ k [31:0] $end
$scope module the_circuit $end
$var wire 1 ! clk $end
$var reg 5 % counter [4:0] $end
$var reg 5 & counterB [4:0] $end
$var reg 1 ' dashflag $end
$var reg 1 " dataOut $end
$var reg 1 ( dotflag $end
$var reg 1 ) startCounterB $end
$var reg 4 * state [3:0] $end
$upscope $end
$upscope $end
$enddefinitions $end
#0
$dumpvars
bx *
x)
x(
x'
bx &
bx %
b0 $
0#
x"
0!
$end
#100
0)
b0 &
b0 %
0'
0(
b0 *
b1 $
1!
1#
#200
b10 $
0!
0#
#300
b1 *
0"
b1 %
b11 $
1!
1#
#400
b100 $
0!
0#
#500
b0 *
1"
b10 %
b101 $
1!
1#
#600
b110 $
0!
0#
#700
b1 *
0"
b11 %
b111 $
1!
1#
#800
b1000 $
0!
0#
#900
b0 *
1"
b100 %
b1001 $
1!
1#
#1000
b1010 $
0!
0#
#1100
b1 *
0"
b101 %
b1011 $
1!
1#
#1200
b1100 $
0!
0#
#1300
b0 *
1"
1(
b0 %
b1101 $
1!
1#
#1400
b1110 $
0!
0#
#1500
b11 *
0"
b1 %
b1111 $
1!
1#
#1600
b10000 $
0!
0#
#1700
b100 *
b10 %
b10001 $
1!
1#
#1800
b10010 $
0!
0#
#1900
b1 *
b11 %
b10011 $
1!
1#
#2000
b10100 $
0!
0#
#2100
1)
b101 *
1"
b0 %
b10101 $
1!
1#
#2200
b10110 $
0!
0#
#2300
b110 *
b1 &
b1 %
b10111 $
1!
1#
#2400
b11000 $
0!
0#
#2500
b111 *
b10 &
b10 %
b11001 $
1!
1#
#2600
b11010 $
0!
0#
#2700
b1 *
0"
b11 &
b11 %
b11011 $
1!
1#
#2800
b11100 $
0!
0#
#2900
b101 *
1"
b100 &
b0 %
b11101 $
1!
1#
#3000
b11110 $
0!
0#
#3100
b110 *
b101 &
b1 %
b11111 $
1!
1#
#3200
b100000 $
0!
0#
#3300
b111 *
b110 &
b10 %
b100001 $
1!
1#
#3400
b100010 $
0!
0#
#3500
b1 *
0"
b111 &
b11 %
b100011 $
1!
1#
#3600
b100100 $
0!
0#
#3700
b101 *
1"
b1000 &
b0 %
b100101 $
1!
1#
#3800
b100110 $
0!
0#
#3900
b110 *
b1001 &
b1 %
b100111 $
1!
1#
#4000
b101000 $
0!
0#
#4100
b111 *
1'
b0 &
b10 %
b101001 $
1!
1#
#4200
b101010 $
0!
0#
#4300
0)
b100 *
0"
b1 &
b101 %
b101011 $
1!
1#
#4400
b101100 $
0!
0#
#4500
0(
b0 *
b0 %
b101101 $
1!
1#
#4600
b101110 $
0!
0#
#4700
b1 *
b1 %
b101111 $
1!
1#
#4800
b110000 $
0!
0#
#4900
b0 *
1"
b10 %
b110001 $
1!
1#
#5000
b110010 $
0!
0#
#5100
b1 *
0"
b11 %
b110011 $
1!
1#
#5200
b110100 $
0!
0#
#5300
b0 *
1"
b100 %
b110101 $
1!
1#
#5400
b110110 $
0!
0#
#5500
b1 *
0"
b101 %
b110111 $
1!
1#
#5600
b111000 $
0!
0#
#5700
b0 *
1"
1(
b0 %
b111001 $
1!
1#
#5800
b111010 $
0!
0#
#5900
b11 *
0"
b1 %
b111011 $
1!
1#
#6000
b111100 $
0!
0#
#6100
0'
b100 *
b10 %
b111101 $
1!
1#
#6200
b111110 $
0!
0#
#6300
b1 *
b11 %
b111111 $
1!
1#
#6400
b1000000 $
0!
0#
#6500
1)
b101 *
1"
b0 %
b1000001 $
1!
1#
#6600
b1000010 $
0!
0#
#6700
b110 *
b10 &
b1 %
b1000011 $
1!
1#
#6800
b1000100 $
0!
0#
#6900
b111 *
b11 &
b10 %
b1000101 $
1!
1#
#7000
b1000110 $
0!
0#
#7100
b1 *
0"
b100 &
b11 %
b1000111 $
1!
1#
#7200
b1001000 $
0!
0#
#7300
b101 *
1"
b101 &
b0 %
b1001001 $
1!
1#
#7400
b1001010 $
0!
0#
#7500
b110 *
b110 &
b1 %
b1001011 $
1!
1#
#7600
b1001100 $
0!
0#
#7700
b111 *
b111 &
b10 %
b1001101 $
1!
1#
#7800
b1001110 $
0!
0#
#7900
b1 *
0"
b1000 &
b11 %
b1001111 $
1!
1#
#8000
b1010000 $
0!
0#
#8100
b101 *
1"
b1001 &
b0 %
b1010001 $
1!
1#
#8200
b1010010 $
0!
0#
#8300
b110 *
1'
b0 &
b1 %
b1010011 $
1!
1#
#8400
b1010100 $
0!
0#
#8500
b111 *
b1 &
b10 %
b1010101 $
1!
1#
#8600
b1010110 $
0!
0#
#8700
0)
b100 *
0"
b10 &
b101 %
b1010111 $
1!
1#
#8800
b1011000 $
0!
0#
#8900
0(
b0 *
b0 %
b1011001 $
1!
1#
#9000
b1011010 $
0!
0#
#9100
b1 *
b1 %
b1011011 $
1!
1#
#9200
b1011100 $
0!
0#
#9300
b0 *
1"
b10 %
b1011101 $
1!
1#
#9400
b1011110 $
0!
0#
#9500
b1 *
0"
b11 %
b1011111 $
1!
1#
#9600
b1100000 $
0!
0#
#9700
b0 *
1"
b100 %
b1100001 $
1!
1#
#9800
b1100010 $
0!
0#
#9900
b1 *
0"
b101 %
b1100011 $
1!
1#
#10000
b1100100 $
0!
0#
#10100
b0 *
1"
1(
b0 %
b1100101 $
1!
1#
#10200
b1100110 $
0!
0#
#10300
b11 *
0"
b1 %
b1100111 $
1!
1#
#10400
b1101000 $
0!
0#
#10500
0'
b100 *
b10 %
b1101001 $
1!
1#
#10600
b1101010 $
0!
0#
#10700
b1 *
b11 %
b1101011 $
1!
1#
#10800
b1101100 $
0!
0#
#10900
1)
b101 *
1"
b0 %
b1101101 $
1!
1#
#11000
b1101110 $
0!
0#
#11100
b110 *
b11 &
b1 %
b1101111 $
1!
1#
#11200
b1110000 $
0!
0#
#11300
b111 *
b100 &
b10 %
b1110001 $
1!
1#
#11400
b1110010 $
0!
0#
#11500
b1 *
0"
b101 &
b11 %
b1110011 $
1!
1#
#11600
b1110100 $
0!
0#
#11700
b101 *
1"
b110 &
b0 %
b1110101 $
1!
1#
#11800
b1110110 $
0!
0#
#11900
b110 *
b111 &
b1 %
b1110111 $
1!
1#
#12000
b1111000 $
0!
0#
#12100
b111 *
b1000 &
b10 %
b1111001 $
1!
1#
#12200
b1111010 $
0!
0#
#12300
b1 *
0"
b1001 &
b11 %
b1111011 $
1!
1#
#12400
b1111100 $
0!
0#
#12500
b101 *
1"
1'
b0 &
b0 %
b1111101 $
1!
1#
#12600
b1111110 $
0!
0#
#12700
b110 *
b1 &
b1 %
b1111111 $
1!
1#
#12800
b10000000 $
0!
0#
